{
  "routes": [
    {
      "method": "GET",
      "path": "/video-galleries",
      "handler": "video-gallery.find",
      "config": {
        "policies": []
      }
    },
    {
      "method": "GET",
      "path": "/video-galleries/count",
      "handler": "video-gallery.count",
      "config": {
        "policies": []
      }
    },
    {
      "method": "GET",
      "path": "/video-galleries/:id",
      "handler": "video-gallery.findOne",
      "config": {
        "policies": []
      }
    },
    {
      "method": "POST",
      "path": "/video-galleries",
      "handler": "video-gallery.create",
      "config": {
        "policies": []
      }
    },
    {
      "method": "PUT",
      "path": "/video-galleries/:id",
      "handler": "video-gallery.update",
      "config": {
        "policies": []
      }
    },
    {
      "method": "DELETE",
      "path": "/video-galleries/:id",
      "handler": "video-gallery.delete",
      "config": {
        "policies": []
      }
    }
  ]
}
